{
  "last_updated": "2026-07-15T00:01:23.429Z",
  "entries": [
    {
      "key": "w.cmine.ynahfkabdajbh01",
      "type": "worker_anomaly",
      "provider": "Dataprana",
      "group_id": "U1+U2",
      "account": "cmine",
      "account_name": "Cyberian Mine",
      "worker": "ynahfkabdajbh01",
      "anomaly_type": "level_drop",
      "baseline_hr": 3044000000000000,
      "current_hr": 0,
      "drop_pct": 100,
      "detected_at": "2026-07-06T17:01:10.692Z",
      "duration_h": 199
    },
    {
      "key": "w.cmine.ynahfkabdajba01",
      "type": "worker_anomaly",
      "provider": "Dataprana",
      "group_id": "U1+U2",
      "account": "cmine",
      "account_name": "Cyberian Mine",
      "worker": "ynahfkabdajba01",
      "anomaly_type": "level_drop",
      "baseline_hr": 237600000000000,
      "current_hr": 0,
      "drop_pct": 100,
      "detected_at": "2026-07-06T17:01:10.692Z",
      "duration_h": 199
    },
    {
      "key": "w.cmine.ngsbfmabdjiaj02",
      "type": "worker_anomaly",
      "provider": "Dataprana",
      "group_id": "U1+U2",
      "account": "cmine",
      "account_name": "Cyberian Mine",
      "worker": "ngsbfmabdjiaj02",
      "anomaly_type": "volatile",
      "baseline_hr": 5021400000000000,
      "current_hr": 0,
      "drop_pct": 100,
      "detected_at": "2026-07-06T17:01:10.692Z",
      "duration_h": 199
    },
    {
      "key": "w.cmine.ynahfkabdajbh02",
      "type": "worker_anomaly",
      "provider": "Dataprana",
      "group_id": "U1+U2",
      "account": "cmine",
      "account_name": "Cyberian Mine",
      "worker": "ynahfkabdajbh02",
      "anomaly_type": "level_drop",
      "baseline_hr": 1036099999999999.9,
      "current_hr": 0,
      "drop_pct": 100,
      "detected_at": "2026-07-06T17:01:10.692Z",
      "duration_h": 199
    },
    {
      "key": "w.cmine.ynahfkabdjiai08",
      "type": "worker_anomaly",
      "provider": "Dataprana",
      "group_id": "U1+U2",
      "account": "cmine",
      "account_name": "Cyberian Mine",
      "worker": "ynahfkabdjiai08",
      "anomaly_type": "volatile",
      "baseline_hr": 461700000000000,
      "current_hr": 0,
      "drop_pct": 100,
      "detected_at": "2026-07-06T17:01:10.692Z",
      "duration_h": 199
    },
    {
      "key": "w.everminer.dgahfkabdjfae06",
      "type": "worker_anomaly",
      "provider": "Dataprana",
      "group_id": "U1+U2",
      "account": "everminer",
      "account_name": "Everminer",
      "worker": "dgahfkabdjfae06",
      "anomaly_type": "level_drop",
      "baseline_hr": 442600000000000,
      "current_hr": 0,
      "drop_pct": 100,
      "detected_at": "2026-07-06T17:01:10.692Z",
      "duration_h": 199
    },
    {
      "key": "w.everminer.ynahfkabdjiai04",
      "type": "worker_anomaly",
      "provider": "Dataprana",
      "group_id": "U1+U2",
      "account": "everminer",
      "account_name": "Everminer",
      "worker": "ynahfkabdjiai04",
      "anomaly_type": "volatile",
      "baseline_hr": 212100000000000,
      "current_hr": 0,
      "drop_pct": 100,
      "detected_at": "2026-07-06T17:01:10.692Z",
      "duration_h": 199
    },
    {
      "key": "w.everminer.dgahfkabdjfae04",
      "type": "worker_anomaly",
      "provider": "Dataprana",
      "group_id": "U1+U2",
      "account": "everminer",
      "account_name": "Everminer",
      "worker": "dgahfkabdjfae04",
      "anomaly_type": "volatile",
      "baseline_hr": 1293700000000000,
      "current_hr": 0,
      "drop_pct": 100,
      "detected_at": "2026-07-06T17:01:10.692Z",
      "duration_h": 199
    },
    {
      "key": "w.everminer.ynahfkabdajbh02",
      "type": "worker_anomaly",
      "provider": "Dataprana",
      "group_id": "U1+U2",
      "account": "everminer",
      "account_name": "Everminer",
      "worker": "ynahfkabdajbh02",
      "anomaly_type": "volatile",
      "baseline_hr": 443600000000000,
      "current_hr": 0,
      "drop_pct": 100,
      "detected_at": "2026-07-06T17:01:10.692Z",
      "duration_h": 199
    },
    {
      "key": "w.everminer.piemfmabdajcj01",
      "type": "worker_anomaly",
      "provider": "Dataprana",
      "group_id": "U1+U2",
      "account": "everminer",
      "account_name": "Everminer",
      "worker": "piemfmabdajcj01",
      "anomaly_type": "volatile",
      "baseline_hr": 2733800000000000,
      "current_hr": 0,
      "drop_pct": 100,
      "detected_at": "2026-07-06T17:01:10.692Z",
      "duration_h": 199
    },
    {
      "key": "w.everminer.ngsbfmabdjiaj02",
      "type": "worker_anomaly",
      "provider": "Dataprana",
      "group_id": "U1+U2",
      "account": "everminer",
      "account_name": "Everminer",
      "worker": "ngsbfmabdjiaj02",
      "anomaly_type": "volatile",
      "baseline_hr": 4096700000000000,
      "current_hr": 0,
      "drop_pct": 100,
      "detected_at": "2026-07-06T17:01:10.692Z",
      "duration_h": 199
    },
    {
      "key": "w.everminer.olttfkabdjfje01",
      "type": "worker_anomaly",
      "provider": "Dataprana",
      "group_id": "U1+U2",
      "account": "everminer",
      "account_name": "Everminer",
      "worker": "olttfkabdjfje01",
      "anomaly_type": "volatile",
      "baseline_hr": 1090500000000000,
      "current_hr": 0,
      "drop_pct": 100,
      "detected_at": "2026-07-06T17:01:10.692Z",
      "duration_h": 199
    },
    {
      "key": "w.everminer.ynahfkabdajbh01",
      "type": "worker_anomaly",
      "provider": "Dataprana",
      "group_id": "U1+U2",
      "account": "everminer",
      "account_name": "Everminer",
      "worker": "ynahfkabdajbh01",
      "anomaly_type": "volatile",
      "baseline_hr": 1830300000000000,
      "current_hr": 0,
      "drop_pct": 100,
      "detected_at": "2026-07-06T17:01:10.692Z",
      "duration_h": 199
    },
    {
      "key": "w.cmine.s21xp003",
      "type": "worker_anomaly",
      "provider": "Altos",
      "group_id": "P1",
      "account": "cmine",
      "account_name": "Cyberian Mine",
      "worker": "s21xp003",
      "anomaly_type": "volatile",
      "baseline_hr": 476800000000000,
      "current_hr": 0,
      "drop_pct": 100,
      "detected_at": "2026-07-07T13:01:18.277Z",
      "duration_h": 179
    },
    {
      "key": "w.everminer.k2lx131x5x19",
      "type": "worker_anomaly",
      "provider": "Minto",
      "group_id": "R3",
      "account": "everminer",
      "account_name": "Everminer",
      "worker": "k2lx131x5x19",
      "anomaly_type": "volatile",
      "baseline_hr": 191700000000000,
      "current_hr": 0,
      "drop_pct": 100,
      "detected_at": "2026-07-07T15:01:22.508Z",
      "duration_h": 177
    },
    {
      "key": "w.cmine.k2lx131x4x42",
      "type": "worker_anomaly",
      "provider": "Minto",
      "group_id": "R3",
      "account": "cmine",
      "account_name": "Cyberian Mine",
      "worker": "k2lx131x4x42",
      "anomaly_type": "volatile",
      "baseline_hr": 183600000000000,
      "current_hr": 0,
      "drop_pct": 100,
      "detected_at": "2026-07-08T04:01:17.739Z",
      "duration_h": 164
    },
    {
      "key": "w.cmine.k2lx131x2x46",
      "type": "worker_anomaly",
      "provider": "Minto",
      "group_id": "R3",
      "account": "cmine",
      "account_name": "Cyberian Mine",
      "worker": "k2lx131x2x46",
      "anomaly_type": "level_drop",
      "baseline_hr": 192500000000000,
      "current_hr": 0,
      "drop_pct": 100,
      "detected_at": "2026-07-09T16:31:00.336Z",
      "duration_h": 127.5
    },
    {
      "key": "w.cmine.02a34725b1b2",
      "type": "worker_anomaly",
      "provider": "Dataprana",
      "group_id": "U1+U2",
      "account": "cmine",
      "account_name": "Cyberian Mine",
      "worker": "02a34725b1b2",
      "anomaly_type": "level_drop",
      "baseline_hr": 136400000000000,
      "current_hr": 51290995756163.984,
      "drop_pct": 62,
      "detected_at": "2026-07-09T21:01:11.828Z",
      "duration_h": 123
    },
    {
      "key": "w.cmine.k2lx131x1x38",
      "type": "worker_anomaly",
      "provider": "Minto",
      "group_id": "R3",
      "account": "cmine",
      "account_name": "Cyberian Mine",
      "worker": "k2lx131x1x38",
      "anomaly_type": "volatile",
      "baseline_hr": 153600000000000,
      "current_hr": 0,
      "drop_pct": 100,
      "detected_at": "2026-07-10T13:01:16.296Z",
      "duration_h": 107
    },
    {
      "key": "g.cmine.P1",
      "type": "group_drop",
      "provider": "Altos",
      "group_id": "P1",
      "account": "cmine",
      "account_name": "Cyberian Mine",
      "worker": null,
      "anomaly_type": null,
      "baseline_hr": 11528485296128852,
      "current_hr": 0,
      "drop_pct": 100,
      "detected_at": "2026-07-12T05:31:05.897Z",
      "duration_h": 66.5
    },
    {
      "key": "g.everminer.P1",
      "type": "group_drop",
      "provider": "Altos",
      "group_id": "P1",
      "account": "everminer",
      "account_name": "Everminer",
      "worker": null,
      "anomaly_type": null,
      "baseline_hr": 2942873006505595.5,
      "current_hr": 0,
      "drop_pct": 100,
      "detected_at": "2026-07-12T05:31:05.897Z",
      "duration_h": 66.5
    },
    {
      "key": "w.cmine.s21xp001",
      "type": "worker_anomaly",
      "provider": "Altos",
      "group_id": "P1",
      "account": "cmine",
      "account_name": "Cyberian Mine",
      "worker": "s21xp001",
      "anomaly_type": "volatile",
      "baseline_hr": 471600000000000,
      "current_hr": 0,
      "drop_pct": 100,
      "detected_at": "2026-07-12T06:31:08.479Z",
      "duration_h": 65.5
    },
    {
      "key": "w.cmine.s21xphyd0002",
      "type": "worker_anomaly",
      "provider": "Altos",
      "group_id": "P1",
      "account": "cmine",
      "account_name": "Cyberian Mine",
      "worker": "s21xphyd0002",
      "anomaly_type": "volatile",
      "baseline_hr": 472900000000000,
      "current_hr": 0,
      "drop_pct": 100,
      "detected_at": "2026-07-12T06:31:08.479Z",
      "duration_h": 65.5
    },
    {
      "key": "w.cmine.s21xphyd005",
      "type": "worker_anomaly",
      "provider": "Altos",
      "group_id": "P1",
      "account": "cmine",
      "account_name": "Cyberian Mine",
      "worker": "s21xphyd005",
      "anomaly_type": "volatile",
      "baseline_hr": 475200000000000,
      "current_hr": 0,
      "drop_pct": 100,
      "detected_at": "2026-07-12T06:31:08.479Z",
      "duration_h": 65.5
    },
    {
      "key": "w.cmine.s21xphyd006",
      "type": "worker_anomaly",
      "provider": "Altos",
      "group_id": "P1",
      "account": "cmine",
      "account_name": "Cyberian Mine",
      "worker": "s21xphyd006",
      "anomaly_type": "volatile",
      "baseline_hr": 480100000000000,
      "current_hr": 0,
      "drop_pct": 100,
      "detected_at": "2026-07-12T06:31:08.479Z",
      "duration_h": 65.5
    },
    {
      "key": "w.cmine.s21xphyd007",
      "type": "worker_anomaly",
      "provider": "Altos",
      "group_id": "P1",
      "account": "cmine",
      "account_name": "Cyberian Mine",
      "worker": "s21xphyd007",
      "anomaly_type": "volatile",
      "baseline_hr": 476800000000000,
      "current_hr": 0,
      "drop_pct": 100,
      "detected_at": "2026-07-12T06:31:08.479Z",
      "duration_h": 65.5
    },
    {
      "key": "w.cmine.s21xp005",
      "type": "worker_anomaly",
      "provider": "Altos",
      "group_id": "P1",
      "account": "cmine",
      "account_name": "Cyberian Mine",
      "worker": "s21xp005",
      "anomaly_type": "volatile",
      "baseline_hr": 470100000000000,
      "current_hr": 0,
      "drop_pct": 100,
      "detected_at": "2026-07-12T06:31:08.479Z",
      "duration_h": 65.5
    },
    {
      "key": "w.cmine.s21xphyd001",
      "type": "worker_anomaly",
      "provider": "Altos",
      "group_id": "P1",
      "account": "cmine",
      "account_name": "Cyberian Mine",
      "worker": "s21xphyd001",
      "anomaly_type": "volatile",
      "baseline_hr": 469000000000000,
      "current_hr": 0,
      "drop_pct": 100,
      "detected_at": "2026-07-12T06:31:08.479Z",
      "duration_h": 65.5
    },
    {
      "key": "w.cmine.s21hyd008",
      "type": "worker_anomaly",
      "provider": "Altos",
      "group_id": "P1",
      "account": "cmine",
      "account_name": "Cyberian Mine",
      "worker": "s21hyd008",
      "anomaly_type": "volatile",
      "baseline_hr": 367100000000000,
      "current_hr": 0,
      "drop_pct": 100,
      "detected_at": "2026-07-12T06:31:08.479Z",
      "duration_h": 65.5
    },
    {
      "key": "w.cmine.s21xphyd0001",
      "type": "worker_anomaly",
      "provider": "Altos",
      "group_id": "P1",
      "account": "cmine",
      "account_name": "Cyberian Mine",
      "worker": "s21xphyd0001",
      "anomaly_type": "volatile",
      "baseline_hr": 483600000000000,
      "current_hr": 0,
      "drop_pct": 100,
      "detected_at": "2026-07-12T06:31:08.479Z",
      "duration_h": 65.5
    },
    {
      "key": "w.cmine.s21hyd009",
      "type": "worker_anomaly",
      "provider": "Altos",
      "group_id": "P1",
      "account": "cmine",
      "account_name": "Cyberian Mine",
      "worker": "s21hyd009",
      "anomaly_type": "volatile",
      "baseline_hr": 368200000000000,
      "current_hr": 0,
      "drop_pct": 100,
      "detected_at": "2026-07-12T06:31:08.479Z",
      "duration_h": 65.5
    },
    {
      "key": "w.cmine.s21hyd002",
      "type": "worker_anomaly",
      "provider": "Altos",
      "group_id": "P1",
      "account": "cmine",
      "account_name": "Cyberian Mine",
      "worker": "s21hyd002",
      "anomaly_type": "volatile",
      "baseline_hr": 360600000000000,
      "current_hr": 0,
      "drop_pct": 100,
      "detected_at": "2026-07-12T06:31:08.479Z",
      "duration_h": 65.5
    },
    {
      "key": "w.cmine.s21hyd006",
      "type": "worker_anomaly",
      "provider": "Altos",
      "group_id": "P1",
      "account": "cmine",
      "account_name": "Cyberian Mine",
      "worker": "s21hyd006",
      "anomaly_type": "volatile",
      "baseline_hr": 352900000000000,
      "current_hr": 0,
      "drop_pct": 100,
      "detected_at": "2026-07-12T06:31:08.479Z",
      "duration_h": 65.5
    },
    {
      "key": "w.cmine.s21xphyd002",
      "type": "worker_anomaly",
      "provider": "Altos",
      "group_id": "P1",
      "account": "cmine",
      "account_name": "Cyberian Mine",
      "worker": "s21xphyd002",
      "anomaly_type": "volatile",
      "baseline_hr": 462000000000000,
      "current_hr": 0,
      "drop_pct": 100,
      "detected_at": "2026-07-12T06:31:08.479Z",
      "duration_h": 65.5
    },
    {
      "key": "w.cmine.s21xphyd0004",
      "type": "worker_anomaly",
      "provider": "Altos",
      "group_id": "P1",
      "account": "cmine",
      "account_name": "Cyberian Mine",
      "worker": "s21xphyd0004",
      "anomaly_type": "volatile",
      "baseline_hr": 490500000000000,
      "current_hr": 0,
      "drop_pct": 100,
      "detected_at": "2026-07-12T06:31:08.479Z",
      "duration_h": 65.5
    },
    {
      "key": "w.cmine.s21hyd001",
      "type": "worker_anomaly",
      "provider": "Altos",
      "group_id": "P1",
      "account": "cmine",
      "account_name": "Cyberian Mine",
      "worker": "s21hyd001",
      "anomaly_type": "volatile",
      "baseline_hr": 350700000000000,
      "current_hr": 0,
      "drop_pct": 100,
      "detected_at": "2026-07-12T06:31:08.479Z",
      "duration_h": 65.5
    },
    {
      "key": "w.cmine.s21hyd003",
      "type": "worker_anomaly",
      "provider": "Altos",
      "group_id": "P1",
      "account": "cmine",
      "account_name": "Cyberian Mine",
      "worker": "s21hyd003",
      "anomaly_type": "level_drop",
      "baseline_hr": 413400000000000,
      "current_hr": 0,
      "drop_pct": 100,
      "detected_at": "2026-07-12T06:31:08.479Z",
      "duration_h": 65.5
    },
    {
      "key": "w.cmine.s21hyd010",
      "type": "worker_anomaly",
      "provider": "Altos",
      "group_id": "P1",
      "account": "cmine",
      "account_name": "Cyberian Mine",
      "worker": "s21hyd010",
      "anomaly_type": "volatile",
      "baseline_hr": 397900000000000,
      "current_hr": 0,
      "drop_pct": 100,
      "detected_at": "2026-07-12T06:31:08.479Z",
      "duration_h": 65.5
    },
    {
      "key": "w.cmine.s21xphyd0003",
      "type": "worker_anomaly",
      "provider": "Altos",
      "group_id": "P1",
      "account": "cmine",
      "account_name": "Cyberian Mine",
      "worker": "s21xphyd0003",
      "anomaly_type": "volatile",
      "baseline_hr": 489300000000000,
      "current_hr": 0,
      "drop_pct": 100,
      "detected_at": "2026-07-12T06:31:08.479Z",
      "duration_h": 65.5
    },
    {
      "key": "w.cmine.s21xp006",
      "type": "worker_anomaly",
      "provider": "Altos",
      "group_id": "P1",
      "account": "cmine",
      "account_name": "Cyberian Mine",
      "worker": "s21xp006",
      "anomaly_type": "volatile",
      "baseline_hr": 493600000000000,
      "current_hr": 0,
      "drop_pct": 100,
      "detected_at": "2026-07-12T06:31:08.479Z",
      "duration_h": 65.5
    },
    {
      "key": "w.cmine.s21xphyd003",
      "type": "worker_anomaly",
      "provider": "Altos",
      "group_id": "P1",
      "account": "cmine",
      "account_name": "Cyberian Mine",
      "worker": "s21xphyd003",
      "anomaly_type": "volatile",
      "baseline_hr": 497000000000000,
      "current_hr": 0,
      "drop_pct": 100,
      "detected_at": "2026-07-12T06:31:08.479Z",
      "duration_h": 65.5
    },
    {
      "key": "w.cmine.s21hyd005",
      "type": "worker_anomaly",
      "provider": "Altos",
      "group_id": "P1",
      "account": "cmine",
      "account_name": "Cyberian Mine",
      "worker": "s21hyd005",
      "anomaly_type": "volatile",
      "baseline_hr": 406600000000000,
      "current_hr": 0,
      "drop_pct": 100,
      "detected_at": "2026-07-12T06:31:08.479Z",
      "duration_h": 65.5
    },
    {
      "key": "w.cmine.s21xphyd004",
      "type": "worker_anomaly",
      "provider": "Altos",
      "group_id": "P1",
      "account": "cmine",
      "account_name": "Cyberian Mine",
      "worker": "s21xphyd004",
      "anomaly_type": "volatile",
      "baseline_hr": 457300000000000,
      "current_hr": 0,
      "drop_pct": 100,
      "detected_at": "2026-07-12T06:31:08.479Z",
      "duration_h": 65.5
    },
    {
      "key": "w.cmine.s21hyd012",
      "type": "worker_anomaly",
      "provider": "Altos",
      "group_id": "P1",
      "account": "cmine",
      "account_name": "Cyberian Mine",
      "worker": "s21hyd012",
      "anomaly_type": "volatile",
      "baseline_hr": 396300000000000,
      "current_hr": 0,
      "drop_pct": 100,
      "detected_at": "2026-07-12T06:31:08.479Z",
      "duration_h": 65.5
    },
    {
      "key": "w.cmine.s21hyd011",
      "type": "worker_anomaly",
      "provider": "Altos",
      "group_id": "P1",
      "account": "cmine",
      "account_name": "Cyberian Mine",
      "worker": "s21hyd011",
      "anomaly_type": "volatile",
      "baseline_hr": 360300000000000,
      "current_hr": 0,
      "drop_pct": 100,
      "detected_at": "2026-07-12T06:31:08.479Z",
      "duration_h": 65.5
    },
    {
      "key": "w.everminer.s21hyd001",
      "type": "worker_anomaly",
      "provider": "Altos",
      "group_id": "P1",
      "account": "everminer",
      "account_name": "Everminer",
      "worker": "s21hyd001",
      "anomaly_type": "volatile",
      "baseline_hr": 392600000000000,
      "current_hr": 0,
      "drop_pct": 100,
      "detected_at": "2026-07-12T06:31:08.479Z",
      "duration_h": 65.5
    },
    {
      "key": "w.everminer.s21hyd002",
      "type": "worker_anomaly",
      "provider": "Altos",
      "group_id": "P1",
      "account": "everminer",
      "account_name": "Everminer",
      "worker": "s21hyd002",
      "anomaly_type": "volatile",
      "baseline_hr": 346400000000000,
      "current_hr": 0,
      "drop_pct": 100,
      "detected_at": "2026-07-12T06:31:08.479Z",
      "duration_h": 65.5
    },
    {
      "key": "w.everminer.s21hyd005",
      "type": "worker_anomaly",
      "provider": "Altos",
      "group_id": "P1",
      "account": "everminer",
      "account_name": "Everminer",
      "worker": "s21hyd005",
      "anomaly_type": "volatile",
      "baseline_hr": 408500000000000,
      "current_hr": 0,
      "drop_pct": 100,
      "detected_at": "2026-07-12T06:31:08.479Z",
      "duration_h": 65.5
    },
    {
      "key": "w.everminer.s21hyd007",
      "type": "worker_anomaly",
      "provider": "Altos",
      "group_id": "P1",
      "account": "everminer",
      "account_name": "Everminer",
      "worker": "s21hyd007",
      "anomaly_type": "volatile",
      "baseline_hr": 357800000000000,
      "current_hr": 0,
      "drop_pct": 100,
      "detected_at": "2026-07-12T06:31:08.479Z",
      "duration_h": 65.5
    },
    {
      "key": "w.everminer.s21hyd003",
      "type": "worker_anomaly",
      "provider": "Altos",
      "group_id": "P1",
      "account": "everminer",
      "account_name": "Everminer",
      "worker": "s21hyd003",
      "anomaly_type": "volatile",
      "baseline_hr": 409200000000000,
      "current_hr": 0,
      "drop_pct": 100,
      "detected_at": "2026-07-12T06:31:08.479Z",
      "duration_h": 65.5
    },
    {
      "key": "w.everminer.s21hyd008",
      "type": "worker_anomaly",
      "provider": "Altos",
      "group_id": "P1",
      "account": "everminer",
      "account_name": "Everminer",
      "worker": "s21hyd008",
      "anomaly_type": "volatile",
      "baseline_hr": 398300000000000,
      "current_hr": 0,
      "drop_pct": 100,
      "detected_at": "2026-07-12T06:31:08.479Z",
      "duration_h": 65.5
    },
    {
      "key": "w.everminer.s21hyd004",
      "type": "worker_anomaly",
      "provider": "Altos",
      "group_id": "P1",
      "account": "everminer",
      "account_name": "Everminer",
      "worker": "s21hyd004",
      "anomaly_type": "volatile",
      "baseline_hr": 366300000000000,
      "current_hr": 0,
      "drop_pct": 100,
      "detected_at": "2026-07-12T06:31:08.479Z",
      "duration_h": 65.5
    },
    {
      "key": "w.cmine.s21hyd007",
      "type": "worker_anomaly",
      "provider": "Altos",
      "group_id": "P1",
      "account": "cmine",
      "account_name": "Cyberian Mine",
      "worker": "s21hyd007",
      "anomaly_type": "level_drop",
      "baseline_hr": 402200000000000,
      "current_hr": 0,
      "drop_pct": 100,
      "detected_at": "2026-07-12T07:01:11.832Z",
      "duration_h": 65
    },
    {
      "key": "w.cmine.s21xp004",
      "type": "worker_anomaly",
      "provider": "Altos",
      "group_id": "P1",
      "account": "cmine",
      "account_name": "Cyberian Mine",
      "worker": "s21xp004",
      "anomaly_type": "volatile",
      "baseline_hr": 455200000000000,
      "current_hr": 0,
      "drop_pct": 100,
      "detected_at": "2026-07-12T07:01:11.832Z",
      "duration_h": 65
    },
    {
      "key": "w.cmine.s21xphyd008",
      "type": "worker_anomaly",
      "provider": "Altos",
      "group_id": "P1",
      "account": "cmine",
      "account_name": "Cyberian Mine",
      "worker": "s21xphyd008",
      "anomaly_type": "level_drop",
      "baseline_hr": 491600000000000,
      "current_hr": 0,
      "drop_pct": 100,
      "detected_at": "2026-07-12T07:01:11.832Z",
      "duration_h": 65
    },
    {
      "key": "w.cmine.s21xp002",
      "type": "worker_anomaly",
      "provider": "Altos",
      "group_id": "P1",
      "account": "cmine",
      "account_name": "Cyberian Mine",
      "worker": "s21xp002",
      "anomaly_type": "level_drop",
      "baseline_hr": 471600000000000,
      "current_hr": 0,
      "drop_pct": 100,
      "detected_at": "2026-07-12T07:01:11.832Z",
      "duration_h": 65
    },
    {
      "key": "w.everminer.s21hyd006",
      "type": "worker_anomaly",
      "provider": "Altos",
      "group_id": "P1",
      "account": "everminer",
      "account_name": "Everminer",
      "worker": "s21hyd006",
      "anomaly_type": "level_drop",
      "baseline_hr": 407400000000000,
      "current_hr": 0,
      "drop_pct": 100,
      "detected_at": "2026-07-12T07:01:11.832Z",
      "duration_h": 65
    },
    {
      "key": "w.cmine.k2lx131x2x49",
      "type": "worker_anomaly",
      "provider": "Minto",
      "group_id": "R3",
      "account": "cmine",
      "account_name": "Cyberian Mine",
      "worker": "k2lx131x2x49",
      "anomaly_type": "volatile",
      "baseline_hr": 197000000000000,
      "current_hr": 0,
      "drop_pct": 100,
      "detected_at": "2026-07-13T01:31:11.397Z",
      "duration_h": 46.5
    },
    {
      "key": "w.cmine.k2lx131x3x40",
      "type": "worker_anomaly",
      "provider": "Minto",
      "group_id": "R3",
      "account": "cmine",
      "account_name": "Cyberian Mine",
      "worker": "k2lx131x3x40",
      "anomaly_type": "volatile",
      "baseline_hr": 194200000000000,
      "current_hr": 0,
      "drop_pct": 100,
      "detected_at": "2026-07-13T01:31:11.397Z",
      "duration_h": 46.5
    },
    {
      "key": "w.cmine.k2lx131x4x33",
      "type": "worker_anomaly",
      "provider": "Minto",
      "group_id": "R3",
      "account": "cmine",
      "account_name": "Cyberian Mine",
      "worker": "k2lx131x4x33",
      "anomaly_type": "level_drop",
      "baseline_hr": 184400000000000,
      "current_hr": 0,
      "drop_pct": 100,
      "detected_at": "2026-07-13T02:01:20.106Z",
      "duration_h": 46
    },
    {
      "key": "w.cmine.k2lx132x11x35",
      "type": "worker_anomaly",
      "provider": "Minto",
      "group_id": "R3",
      "account": "cmine",
      "account_name": "Cyberian Mine",
      "worker": "k2lx132x11x35",
      "anomaly_type": "level_drop",
      "baseline_hr": 290200000000000,
      "current_hr": 171074235845254.25,
      "drop_pct": 41,
      "detected_at": "2026-07-14T04:01:18.767Z",
      "duration_h": 20
    },
    {
      "key": "w.cmine.k2lx132x10x50",
      "type": "worker_anomaly",
      "provider": "Minto",
      "group_id": "R3",
      "account": "cmine",
      "account_name": "Cyberian Mine",
      "worker": "k2lx132x10x50",
      "anomaly_type": "level_drop",
      "baseline_hr": 192900000000000,
      "current_hr": 127914739416287,
      "drop_pct": 34,
      "detected_at": "2026-07-14T13:01:20.421Z",
      "duration_h": 11
    },
    {
      "key": "w.cmine.c21xp031",
      "type": "worker_anomaly",
      "provider": "ValueHash (NY)",
      "group_id": "U3",
      "account": "cmine",
      "account_name": "Cyberian Mine",
      "worker": "c21xp031",
      "anomaly_type": "volatile",
      "baseline_hr": 253800000000000,
      "current_hr": 0,
      "drop_pct": 100,
      "detected_at": "2026-07-14T18:01:22.123Z",
      "duration_h": 6
    },
    {
      "key": "w.everminer.02a13716759b",
      "type": "worker_anomaly",
      "provider": "Dataprana",
      "group_id": "U1+U2",
      "account": "everminer",
      "account_name": "Everminer",
      "worker": "02a13716759b",
      "anomaly_type": "volatile",
      "baseline_hr": 232800000000000,
      "current_hr": 0,
      "drop_pct": 100,
      "detected_at": "2026-07-14T20:31:18.827Z",
      "duration_h": 3.5
    }
  ]
}