{
  "last_updated": "2026-07-01T16:30:54.668Z",
  "issues": {
    "cmine.c21xp031": {
      "account": "cmine",
      "account_name": "Cyberian Mine",
      "worker": "c21xp031",
      "group_id": "U3",
      "provider": "ValueHash (NY)",
      "type": "volatile",
      "current_avg_ths": 17.6,
      "baseline_avg_ths": 10.2,
      "drop_pct": -73,
      "cv_pct": 224,
      "zero_rate_pct": 83
    },
    "cmine.s21xphyd007": {
      "account": "cmine",
      "account_name": "Cyberian Mine",
      "worker": "s21xphyd007",
      "group_id": "P1",
      "provider": "Altos",
      "type": "volatile",
      "current_avg_ths": 247.3,
      "baseline_avg_ths": 14.3,
      "drop_pct": -1627,
      "cv_pct": 79,
      "zero_rate_pct": 0
    },
    "cmine.s21hyd007": {
      "account": "cmine",
      "account_name": "Cyberian Mine",
      "worker": "s21hyd007",
      "group_id": "P1",
      "provider": "Altos",
      "type": "volatile",
      "current_avg_ths": 227.5,
      "baseline_avg_ths": 16.7,
      "drop_pct": -1265,
      "cv_pct": 59,
      "zero_rate_pct": 0
    },
    "cmine.s21hyd008": {
      "account": "cmine",
      "account_name": "Cyberian Mine",
      "worker": "s21hyd008",
      "group_id": "P1",
      "provider": "Altos",
      "type": "volatile",
      "current_avg_ths": 213.9,
      "baseline_avg_ths": 11.9,
      "drop_pct": -1697,
      "cv_pct": 73,
      "zero_rate_pct": 0
    },
    "cmine.s21hyd009": {
      "account": "cmine",
      "account_name": "Cyberian Mine",
      "worker": "s21hyd009",
      "group_id": "P1",
      "provider": "Altos",
      "type": "volatile",
      "current_avg_ths": 203.8,
      "baseline_avg_ths": 18.7,
      "drop_pct": -991,
      "cv_pct": 76,
      "zero_rate_pct": 0
    },
    "cmine.s21hyd006": {
      "account": "cmine",
      "account_name": "Cyberian Mine",
      "worker": "s21hyd006",
      "group_id": "P1",
      "provider": "Altos",
      "type": "volatile",
      "current_avg_ths": 203.1,
      "baseline_avg_ths": 9.2,
      "drop_pct": -2109,
      "cv_pct": 67,
      "zero_rate_pct": 0
    },
    "cmine.s21hyd003": {
      "account": "cmine",
      "account_name": "Cyberian Mine",
      "worker": "s21hyd003",
      "group_id": "P1",
      "provider": "Altos",
      "type": "volatile",
      "current_avg_ths": 206.4,
      "baseline_avg_ths": 9.9,
      "drop_pct": -1979,
      "cv_pct": 70,
      "zero_rate_pct": 0
    },
    "cmine.s21hyd010": {
      "account": "cmine",
      "account_name": "Cyberian Mine",
      "worker": "s21hyd010",
      "group_id": "P1",
      "provider": "Altos",
      "type": "volatile",
      "current_avg_ths": 220.6,
      "baseline_avg_ths": 17,
      "drop_pct": -1194,
      "cv_pct": 60,
      "zero_rate_pct": 0
    },
    "cmine.s21hyd005": {
      "account": "cmine",
      "account_name": "Cyberian Mine",
      "worker": "s21hyd005",
      "group_id": "P1",
      "provider": "Altos",
      "type": "volatile",
      "current_avg_ths": 191.5,
      "baseline_avg_ths": 23.4,
      "drop_pct": -717,
      "cv_pct": 79,
      "zero_rate_pct": 0
    },
    "cmine.s21hyd012": {
      "account": "cmine",
      "account_name": "Cyberian Mine",
      "worker": "s21hyd012",
      "group_id": "P1",
      "provider": "Altos",
      "type": "volatile",
      "current_avg_ths": 192,
      "baseline_avg_ths": 10.1,
      "drop_pct": -1802,
      "cv_pct": 81,
      "zero_rate_pct": 0
    },
    "cmine.s21hyd011": {
      "account": "cmine",
      "account_name": "Cyberian Mine",
      "worker": "s21hyd011",
      "group_id": "P1",
      "provider": "Altos",
      "type": "volatile",
      "current_avg_ths": 189.9,
      "baseline_avg_ths": 13.8,
      "drop_pct": -1271,
      "cv_pct": 71,
      "zero_rate_pct": 0
    },
    "everminer.e21xp024": {
      "account": "everminer",
      "account_name": "Everminer",
      "worker": "e21xp024",
      "group_id": "U3",
      "provider": "ValueHash (NY)",
      "type": "volatile",
      "current_avg_ths": 14.8,
      "baseline_avg_ths": 17.6,
      "drop_pct": 16,
      "cv_pct": 224,
      "zero_rate_pct": 83
    },
    "everminer.s21hyd001": {
      "account": "everminer",
      "account_name": "Everminer",
      "worker": "s21hyd001",
      "group_id": "P1",
      "provider": "Altos",
      "type": "volatile",
      "current_avg_ths": 220.4,
      "baseline_avg_ths": 16.1,
      "drop_pct": -1268,
      "cv_pct": 74,
      "zero_rate_pct": 0
    },
    "everminer.s21hyd002": {
      "account": "everminer",
      "account_name": "Everminer",
      "worker": "s21hyd002",
      "group_id": "P1",
      "provider": "Altos",
      "type": "volatile",
      "current_avg_ths": 225.6,
      "baseline_avg_ths": 13.5,
      "drop_pct": -1575,
      "cv_pct": 73,
      "zero_rate_pct": 0
    },
    "everminer.s21hyd005": {
      "account": "everminer",
      "account_name": "Everminer",
      "worker": "s21hyd005",
      "group_id": "P1",
      "provider": "Altos",
      "type": "volatile",
      "current_avg_ths": 220.5,
      "baseline_avg_ths": 10.6,
      "drop_pct": -1977,
      "cv_pct": 70,
      "zero_rate_pct": 0
    },
    "everminer.s21hyd007": {
      "account": "everminer",
      "account_name": "Everminer",
      "worker": "s21hyd007",
      "group_id": "P1",
      "provider": "Altos",
      "type": "volatile",
      "current_avg_ths": 185.3,
      "baseline_avg_ths": 15.8,
      "drop_pct": -1071,
      "cv_pct": 64,
      "zero_rate_pct": 0
    },
    "everminer.s21hyd003": {
      "account": "everminer",
      "account_name": "Everminer",
      "worker": "s21hyd003",
      "group_id": "P1",
      "provider": "Altos",
      "type": "volatile",
      "current_avg_ths": 203.8,
      "baseline_avg_ths": 14.7,
      "drop_pct": -1284,
      "cv_pct": 82,
      "zero_rate_pct": 0
    },
    "everminer.e21xp029": {
      "account": "everminer",
      "account_name": "Everminer",
      "worker": "e21xp029",
      "group_id": "U3",
      "provider": "ValueHash (NY)",
      "type": "volatile",
      "current_avg_ths": 8.2,
      "baseline_avg_ths": 13.3,
      "drop_pct": 38,
      "cv_pct": 224,
      "zero_rate_pct": 83
    },
    "everminer.s21hyd008": {
      "account": "everminer",
      "account_name": "Everminer",
      "worker": "s21hyd008",
      "group_id": "P1",
      "provider": "Altos",
      "type": "volatile",
      "current_avg_ths": 204.2,
      "baseline_avg_ths": 9.1,
      "drop_pct": -2136,
      "cv_pct": 83,
      "zero_rate_pct": 0
    },
    "everminer.s21hyd004": {
      "account": "everminer",
      "account_name": "Everminer",
      "worker": "s21hyd004",
      "group_id": "P1",
      "provider": "Altos",
      "type": "volatile",
      "current_avg_ths": 184.8,
      "baseline_avg_ths": 20,
      "drop_pct": -825,
      "cv_pct": 68,
      "zero_rate_pct": 0
    }
  }
}